gitreg/__init__.py
gitreg/main.py
pylaw-0.0.1.dist-info/LICENSE
pylaw-0.0.1.dist-info/METADATA
pylaw-0.0.1.dist-info/WHEEL
pylaw-0.0.1.dist-info/top_level.txt
pylaw-0.0.1.dist-info/RECORD
