Metadata-Version: 2.1
Name: pylaw
Version: 0.0.1
Summary: PyLaw
Home-page: https://pylaw.org/
Author: Maxime Logé
Author-email: maxime.loge@gitreg.com
Project-URL: Bug Tracker, https://gitreg.com/pylaw/issues
Classifier: Programming Language :: Python :: 3
Classifier: License :: OSI Approved :: MIT License
Classifier: Operating System :: OS Independent
Requires-Python: >=3.6
License-File: LICENSE
